SandeepTest/__init__.py
SandeepTest/test.py
helloSandeep-0.0.3.dist-info/METADATA
helloSandeep-0.0.3.dist-info/WHEEL
helloSandeep-0.0.3.dist-info/top_level.txt
helloSandeep-0.0.3.dist-info/RECORD
