Metadata-Version: 2.1
Name: helloSandeep
Version: 0.0.3
Summary: Calling name package
Author: Sandeep Chowdhury
Author-email: <sandeepiit.ism@gmail.com>
Keywords: python,name,hello,sandeep,call
Classifier: Development Status :: 1 - Planning
Classifier: Intended Audience :: Developers
Classifier: Programming Language :: Python :: 3
Classifier: Operating System :: Unix
Classifier: Operating System :: MacOS :: MacOS X
Classifier: Operating System :: Microsoft :: Windows
